annot_utils/__init__.py
annot_utils/boundary.py
annot_utils/chr_name.py
annot_utils/coding.py
annot_utils/exon.py
annot_utils/gene.py
annot_utils/junction.py
annot_utils/logger.py
annot_utils/parser.py
annot_utils/run.py
annot_utils/simple_repeat.py
annot_utils/utils.py
annot_utils/version.py
annot_utils/data/hg19/GCF_000001405.13.assembly.txt
annot_utils/data/hg19/refGene.txt.gz
annot_utils/data/hg19/wgEncodeGencodeBasicV19.txt.gz
annot_utils/data/hg38/GCF_000001405.26.assembly.txt
annot_utils/data/hg38/refGene.txt.gz
annot_utils/data/hg38/wgEncodeGencodeBasicV28.txt.gz
annot_utils/data/mm10/GCF_000001635.20.assembly.txt
annot_utils/data/mm10/refGene.txt.gz
annot_utils/data/mm10/wgEncodeGencodeBasicVM18.txt.gz
annot_utils-0.3.0b1.dist-info/LICENSE
annot_utils-0.3.0b1.dist-info/METADATA
annot_utils-0.3.0b1.dist-info/WHEEL
annot_utils-0.3.0b1.dist-info/entry_points.txt
annot_utils-0.3.0b1.dist-info/top_level.txt
annot_utils-0.3.0b1.dist-info/RECORD
